doped/__init__.py
doped/analysis.py
doped/chemical_potentials.py
doped/core.py
doped/corrections.py
doped/generation.py
doped/py.typed
doped/thermodynamics.py
doped/vasp.py
doped/VASP_sets/DefectSet.yaml
doped/VASP_sets/HSESet.yaml
doped/VASP_sets/PBEsol_ConvergenceSet.yaml
doped/VASP_sets/PotcarSet.yaml
doped/VASP_sets/RelaxSet.yaml
doped/utils/__init__.py
doped/utils/configurations.py
doped/utils/displacement.mplstyle
doped/utils/displacements.py
doped/utils/doped.mplstyle
doped/utils/efficiency.py
doped/utils/eigenvalues.py
doped/utils/legacy_corrections.py
doped/utils/parsing.py
doped/utils/plotting.py
doped/utils/supercells.py
doped/utils/symmetry.py
doped/utils/wyckpos.dat
doped-3.2.0.dist-info/licenses/LICENSE
doped-3.2.0.dist-info/METADATA
doped-3.2.0.dist-info/WHEEL
doped-3.2.0.dist-info/top_level.txt
doped-3.2.0.dist-info/RECORD
