Metadata-Version: 2.4
Name: doped
Version: 3.2.0
Summary: Python package to setup, process and analyse solid-state defect calculations with VASP
Author-email: Seán Kavanagh <skavanagh@seas.harvard.edu>
License: MIT License
Project-URL: Homepage, https://doped.readthedocs.io/en/latest/
Project-URL: Documentation, https://doped.readthedocs.io/en/latest/
Project-URL: Package, https://pypi.org/project/doped/
Project-URL: Repository, https://github.com/SMTG-Bham/doped
Classifier: License :: OSI Approved :: MIT License
Classifier: Programming Language :: Python :: 3
Classifier: Intended Audience :: Science/Research
Classifier: License :: OSI Approved :: MIT License
Classifier: Operating System :: OS Independent
Classifier: Topic :: Scientific/Engineering :: Information Analysis
Classifier: Topic :: Scientific/Engineering :: Physics
Classifier: Topic :: Scientific/Engineering :: Chemistry
Classifier: Topic :: Software Development :: Libraries :: Python Modules
Requires-Python: >=3.10
License-File: LICENSE
Requires-Dist: tabulate
Requires-Dist: matplotlib>=3.5.2
Requires-Dist: numpy>=1.21.0
Requires-Dist: pymatgen>=2025.10.7
Requires-Dist: pymatgen-analysis-defects>=2023.8.22
Requires-Dist: shakenbreak>=3.4.2
Requires-Dist: ase
Requires-Dist: pandas
Requires-Dist: pydefect>=0.9.9
Requires-Dist: filelock
Requires-Dist: vise>=0.9.0
Requires-Dist: cmcrameri>=1.4
Requires-Dist: matplotlib-label-lines
Requires-Dist: dscribe
Provides-Extra: tests
Requires-Dist: pytest>=8.3; extra == "tests"
Requires-Dist: pytest-mpl>=0.16.1; extra == "tests"
Requires-Dist: py-sc-fermi; extra == "tests"
Requires-Dist: pytest-split>=0.10.0; extra == "tests"
Provides-Extra: docs
Requires-Dist: sphinx>7; extra == "docs"
Requires-Dist: myst-nb>=1.0; extra == "docs"
Requires-Dist: recommonmark; extra == "docs"
Requires-Dist: renku-sphinx-theme>=0.5.0; extra == "docs"
Requires-Dist: sphinx_rtd_theme>=2.0; extra == "docs"
Requires-Dist: sphinx_design; extra == "docs"
Requires-Dist: sphinx_click; extra == "docs"
Provides-Extra: analysis
Requires-Dist: easyunfold; extra == "analysis"
Requires-Dist: py-sc-fermi; extra == "analysis"
Requires-Dist: sumo; extra == "analysis"
Requires-Dist: nonrad; extra == "analysis"
Provides-Extra: pdf
Requires-Dist: pycairo; extra == "pdf"
Dynamic: license-file
